AUTHORS
LICENSE
MANIFEST.in
README.rst
pyproject.toml
requirements.txt
setup.cfg
setup.py
wx_icons_adwaita/__init__.py
wx_icons_adwaita/py.typed
wx_icons_adwaita.egg-info/PKG-INFO
wx_icons_adwaita.egg-info/SOURCES.txt
wx_icons_adwaita.egg-info/dependency_links.txt
wx_icons_adwaita.egg-info/not-zip-safe
wx_icons_adwaita.egg-info/requires.txt
wx_icons_adwaita.egg-info/top_level.txt
wx_icons_adwaita/Adwaita/__init__.py
wx_icons_adwaita/Adwaita/index.theme
wx_icons_adwaita/Adwaita/16x16/actions/address-book-new.png
wx_icons_adwaita/Adwaita/16x16/actions/application-exit.png
wx_icons_adwaita/Adwaita/16x16/actions/appointment-new.png
wx_icons_adwaita/Adwaita/16x16/actions/bookmark-new.png
wx_icons_adwaita/Adwaita/16x16/actions/call-start.png
wx_icons_adwaita/Adwaita/16x16/actions/call-stop.png
wx_icons_adwaita/Adwaita/16x16/actions/contact-new.png
wx_icons_adwaita/Adwaita/16x16/actions/document-new.png
wx_icons_adwaita/Adwaita/16x16/actions/document-open-recent.png
wx_icons_adwaita/Adwaita/16x16/actions/document-open.png
wx_icons_adwaita/Adwaita/16x16/actions/document-page-setup.png
wx_icons_adwaita/Adwaita/16x16/actions/document-print-preview.png
wx_icons_adwaita/Adwaita/16x16/actions/document-print.png
wx_icons_adwaita/Adwaita/16x16/actions/document-properties.png
wx_icons_adwaita/Adwaita/16x16/actions/document-revert-rtl.png
wx_icons_adwaita/Adwaita/16x16/actions/document-revert.png
wx_icons_adwaita/Adwaita/16x16/actions/document-save-as.png
wx_icons_adwaita/Adwaita/16x16/actions/document-save.png
wx_icons_adwaita/Adwaita/16x16/actions/document-send.png
wx_icons_adwaita/Adwaita/16x16/actions/edit-clear-all.png
wx_icons_adwaita/Adwaita/16x16/actions/edit-clear-rtl.png
wx_icons_adwaita/Adwaita/16x16/actions/edit-clear.png
wx_icons_adwaita/Adwaita/16x16/actions/edit-copy.png
wx_icons_adwaita/Adwaita/16x16/actions/edit-cut.png
wx_icons_adwaita/Adwaita/16x16/actions/edit-delete.png
wx_icons_adwaita/Adwaita/16x16/actions/edit-find-replace.png
wx_icons_adwaita/Adwaita/16x16/actions/edit-find.png
wx_icons_adwaita/Adwaita/16x16/actions/edit-paste.png
wx_icons_adwaita/Adwaita/16x16/actions/edit-redo-rtl.png
wx_icons_adwaita/Adwaita/16x16/actions/edit-redo.png
